pilotft/Pilotft.py
pilotft/core/PilotftMiddleware.py
pilotft/core/PilotftParams.py
pilotft/core/PilotftState.py
pilotft/core/PilotftView.py
pilotft/core/__init__.py
pilotft/views/InternalErrorView.py
pilotft/views/NotFoundView.py
pilotft/views/__init__.py
pilotft-0.1.0.dist-info/METADATA
pilotft-0.1.0.dist-info/WHEEL
pilotft-0.1.0.dist-info/top_level.txt
pilotft-0.1.0.dist-info/RECORD
